ovos_cli_client/__init__.py
ovos_cli_client/__main__.py
ovos_cli_client/gui_server.py
ovos_cli_client/text_client.py
ovos_cli_client/version.py
ovos_cli_client-0.0.1a1.dist-info/LICENSE
ovos_cli_client-0.0.1a1.dist-info/METADATA
ovos_cli_client-0.0.1a1.dist-info/WHEEL
ovos_cli_client-0.0.1a1.dist-info/entry_points.txt
ovos_cli_client-0.0.1a1.dist-info/top_level.txt
ovos_cli_client-0.0.1a1.dist-info/RECORD
