Metadata-Version: 2.1
Name: ovos-cli-client
Version: 0.0.1a1
Summary: ovos-core debug cli client
Home-page: https://github.com/OpenVoiceOS/ovos-cli-client
Author: jarbasAI
Author-email: jarbasai@mailfence.com
License: Apache
Platform: UNKNOWN
Requires-Dist: ovos-utils (>=0.0.31a6)
Requires-Dist: ovos-bus-client (>=0.0.3a4,~=0.0)
